dict_validator/__init__.py
dict_validator/dict_field.py
dict_validator/field.py
dict_validator/helpers.py
dict_validator/list_field.py
dict_validator/fields/__init__.py
dict_validator/fields/boolean_field.py
dict_validator/fields/choice_field.py
dict_validator/fields/number_field.py
dict_validator/fields/string_field.py
dict_validator/fields/timestamp_field.py
dict_validator/fields/wildcard_dict_field.py
dict_validator/fields/regexp/__init__.py
dict_validator/fields/regexp/camel_case_field.py
dict_validator/fields/regexp/email_field.py
dict_validator/fields/regexp/name_field.py
dict_validator/fields/regexp/pascal_case_field.py
dict_validator/fields/regexp/phone_field.py
dict_validator/fields/regexp/slug_field.py
dict_validator/fields/regexp/underscore_case_field.py
dict_validator/fields/regexp/url_field.py
dict_validator-5.0.7.dist-info/DESCRIPTION.rst
dict_validator-5.0.7.dist-info/METADATA
dict_validator-5.0.7.dist-info/RECORD
dict_validator-5.0.7.dist-info/WHEEL
dict_validator-5.0.7.dist-info/metadata.json
dict_validator-5.0.7.dist-info/top_level.txt
