Metadata-Version: 2.0
Name: dict-validator
Version: 5.0.7
Summary: A library for structural data validation
Home-page: https://nephilim-solutions.github.io/dict-validator
Author: Anton Berezin
Author-email: anton.berezin@nephilim.solutions
License: Apache-2
Project-URL: Bug Tracker, https://github.com/nephilim-solutions/dict-validator/issues
Project-URL: Documentation, https://nephilim-solutions.github.io/dict-validator
Project-URL: Source Code, https://github.com/nephilim-solutions/dict-validator
Keywords: serialization validation
Platform: UNKNOWN
Classifier: Development Status :: 5 - Production/Stable
Classifier: Intended Audience :: Developers
Classifier: Topic :: Software Development :: Libraries :: Python Modules
Classifier: License :: OSI Approved :: Apache Software License
Classifier: Programming Language :: Python :: 3
